lor_deckcodes/__init__.py
lor_deckcodes/constants.py
lor_deckcodes/decode.py
lor_deckcodes/encode.py
lor_deckcodes/models.py
lor_deckcodes/utils.py
lor_deckcodes-5.0.0.dist-info/LICENSE.txt
lor_deckcodes-5.0.0.dist-info/METADATA
lor_deckcodes-5.0.0.dist-info/WHEEL
lor_deckcodes-5.0.0.dist-info/top_level.txt
lor_deckcodes-5.0.0.dist-info/RECORD
