Metadata-Version: 2.1
Name: lor-deckcodes
Version: 5.0.0
Summary: Legends of Runeterra deck coder and decoder
Home-page: https://github.com/Rafalonso/LoRDeckCodesPython
Author: Rafael Alonso
Maintainer: Rafael Alonso
Maintainer-email: rafalonso.almeida@gmail.com
License: MIT
Classifier: Development Status :: 5 - Production/Stable
Classifier: Intended Audience :: Developers
Classifier: Programming Language :: Python
Classifier: Programming Language :: Python :: 3.5
Classifier: Programming Language :: Python :: 3.6
Classifier: Programming Language :: Python :: 3.7
Classifier: Programming Language :: Python :: 3.8
Classifier: Programming Language :: Python :: 3.9
Classifier: Programming Language :: Python :: 3.10
Classifier: License :: OSI Approved :: MIT License
Requires-Python: >=3.5
License-File: LICENSE.txt
